pyeem/__init__.py
pyeem/_utils.py
pyeem/analysis/__init__.py
pyeem/analysis/basic/__init__.py
pyeem/analysis/basic/base.py
pyeem/analysis/models/__init__.py
pyeem/analysis/models/rutherfordnet.py
pyeem/augmentation/__init__.py
pyeem/augmentation/base.py
pyeem/datasets/__init__.py
pyeem/datasets/demo.py
pyeem/datasets/load.py
pyeem/instruments/__init__.py
pyeem/instruments/base.py
pyeem/instruments/MIT/__init__.py
pyeem/instruments/MIT/remora.py
pyeem/instruments/agilent/__init__.py
pyeem/instruments/agilent/cary_4e.py
pyeem/instruments/agilent/cary_eclipse.py
pyeem/instruments/horiba/__init__.py
pyeem/instruments/horiba/aqualog.py
pyeem/instruments/horiba/fluorolog.py
pyeem/instruments/tecan/__init__.py
pyeem/instruments/tecan/spark.py
pyeem/plots/__init__.py
pyeem/plots/analysis.py
pyeem/plots/augmentations.py
pyeem/plots/base.py
pyeem/plots/preprocessing.py
pyeem/plots/pyeem_base.mplstyle
pyeem/preprocessing/__init__.py
pyeem/preprocessing/routine.py
pyeem/preprocessing/calibration/__init__.py
pyeem/preprocessing/calibration/calibration.py
pyeem/preprocessing/corrections/__init__.py
pyeem/preprocessing/corrections/corrections.py
pyeem/preprocessing/filters/__init__.py
pyeem/preprocessing/filters/filters.py
pyeem-0.2.1.dist-info/DESCRIPTION.rst
pyeem-0.2.1.dist-info/METADATA
pyeem-0.2.1.dist-info/RECORD
pyeem-0.2.1.dist-info/WHEEL
pyeem-0.2.1.dist-info/metadata.json
pyeem-0.2.1.dist-info/top_level.txt
